sequence_server_wrapper/__init__.py
sequence_server_wrapper/_version.py
sequence_server_wrapper/template.py
sequence_server_wrapper/examples/__init__.py
sequence_server_wrapper/examples/example_device.py
sequence_server_wrapper/examples/example_server.py
sequence_server_wrapper/examples/example_server_gui.py
sequence_server_wrapper/examples/example_sync_client.py
sequence_server_wrapper/examples/example_threading_client.py
sequence_server_wrapper/examples/mock_server.py
sequence_server_wrapper/examples/mock_server_client.py
sequence_server_wrapper/tests/__init__.py
sequence_server_wrapper/tests/conftest.py
sequence_server_wrapper/tests/test_examples.py
sequence_server_wrapper/tests/test_server.py
sequence_server_wrapper-0.0.4.dist-info/AUTHORS.rst
sequence_server_wrapper-0.0.4.dist-info/LICENSE
sequence_server_wrapper-0.0.4.dist-info/METADATA
sequence_server_wrapper-0.0.4.dist-info/WHEEL
sequence_server_wrapper-0.0.4.dist-info/entry_points.txt
sequence_server_wrapper-0.0.4.dist-info/top_level.txt
sequence_server_wrapper-0.0.4.dist-info/RECORD
