Metadata-Version: 2.1
Name: sequence-server-wrapper
Version: 0.0.4
Summary: Sequence Server Wrapper
Home-page: https://github.com/vstadnytskyi/sequence-server-wrapper
Author: Valentyn Stadnytskyi
Author-email: v.stadnytskyi@gmail.com
License: BSD (3-clause)
Platform: UNKNOWN
Classifier: Development Status :: 2 - Pre-Alpha
Classifier: Natural Language :: English
Classifier: Programming Language :: Python :: 3
Requires-Python: >=3.6
Requires-Dist: caproto
